[
  {
    "id": 2002,
    "trip_number": "TRP-MH-2002",
    "status": "VEHICLE_BREAKDOWN",
    "origin_city": "Ahmedabad",
    "destination_city": "Surat",
    "origin_address": "GIDC Estate, Odhav, Ahmedabad, GJ 382415",
    "destination_address": "Diamond Hub, Katargam, Surat, GJ 395004",
    "origin_lat": 23.0225,
    "origin_lng": 72.5714,
    "destination_lat": 21.1702,
    "destination_lng": 72.8311,
    "start_date": "2026-03-29T07:00:00Z",
    "expected_delivery_date": "2026-03-29T16:00:00Z",
    "driver_id": 102,
    "driver_name": "Suresh Patel",
    "vehicle_id": 302,
    "vehicle_number": "GJ-01-CD-5678",
    "customer_name": "Reliance Industries",
    "cargo_description": "Textile Fibers",
    "booked_weight_mt": 18.0,
    "total_distance_km": 265.0,
    "freight_amount": 38000.0,
    "budget_estimate": 7000.0,
    "dispatched_at": "2026-03-29T05:00:00Z",
    "accepted_at": "2026-03-29T05:10:00Z",
    "accept_timeout_minutes": 30,
    "active_exception": {
      "type": "VEHICLE_BREAKDOWN",
      "description": "Engine overheating near Vadodara. Vehicle immobilized on NH48.",
      "reported_at": "2026-03-29T10:35:00Z",
      "reported_by_id": 102,
      "reported_by_name": "Suresh Patel",
      "latitude": 22.3072,
      "longitude": 73.1812,
      "resolution_status": "PENDING"
    },
    "milestones": [
      { "id": 1, "type": "DISPATCH", "sequence_number": 1, "status": "COMPLETED", "completed_at": "2026-03-29T05:00:00Z" },
      { "id": 2, "type": "ACCEPT", "sequence_number": 2, "status": "COMPLETED", "completed_at": "2026-03-29T05:10:00Z" },
      { "id": 3, "type": "ARRIVE_ORIGIN", "sequence_number": 3, "status": "COMPLETED", "completed_at": "2026-03-29T06:30:00Z" },
      { "id": 4, "type": "START_LOADING", "sequence_number": 4, "status": "COMPLETED", "completed_at": "2026-03-29T07:00:00Z" },
      { "id": 5, "type": "LOADING_COMPLETE", "sequence_number": 5, "status": "COMPLETED", "completed_at": "2026-03-29T08:00:00Z" },
      { "id": 6, "type": "DEPART", "sequence_number": 6, "status": "COMPLETED", "completed_at": "2026-03-29T08:30:00Z" },
      { "id": 7, "type": "ARRIVE_DESTINATION", "sequence_number": 7, "status": "BLOCKED", "captured_data": { "block_reason": "VEHICLE_BREAKDOWN" } },
      { "id": 8, "type": "START_UNLOADING", "sequence_number": 8, "status": "UPCOMING" },
      { "id": 9, "type": "DELIVERY_COMPLETE", "sequence_number": 9, "status": "UPCOMING" },
      { "id": 10, "type": "SUBMIT_POD", "sequence_number": 10, "status": "UPCOMING" }
    ],
    "documents": [],
    "expenses": []
  }
]
